ShiyongOllydbgConglingkaishiCracking/README.md
ShiyongOllydbgConglingkaishiCracking/__init__.py
ShiyongOllydbgConglingkaishiCracking/__main__.py
ShiyongOllydbgConglingkaishiCracking/file.epub
ShiyongOllydbgConglingkaishiCracking/index.html
ShiyongOllydbgConglingkaishiCracking/css/__init__.py
ShiyongOllydbgConglingkaishiCracking/css/annotations.css
ShiyongOllydbgConglingkaishiCracking/css/main.css
ShiyongOllydbgConglingkaishiCracking/css/normalize.css
ShiyongOllydbgConglingkaishiCracking/css/popup.css
ShiyongOllydbgConglingkaishiCracking/font/__init__.py
ShiyongOllydbgConglingkaishiCracking/font/fontello.eot
ShiyongOllydbgConglingkaishiCracking/font/fontello.svg
ShiyongOllydbgConglingkaishiCracking/font/fontello.ttf
ShiyongOllydbgConglingkaishiCracking/font/fontello.woff
ShiyongOllydbgConglingkaishiCracking/img/__init__.py
ShiyongOllydbgConglingkaishiCracking/img/annotator-glyph-sprite.png
ShiyongOllydbgConglingkaishiCracking/img/annotator-icon-sprite.png
ShiyongOllydbgConglingkaishiCracking/img/apple-touch-icon.png
ShiyongOllydbgConglingkaishiCracking/img/cancelfullscreen.png
ShiyongOllydbgConglingkaishiCracking/img/close.png
ShiyongOllydbgConglingkaishiCracking/img/fullscreen.png
ShiyongOllydbgConglingkaishiCracking/img/loader.gif
ShiyongOllydbgConglingkaishiCracking/img/menu-icon.png
ShiyongOllydbgConglingkaishiCracking/img/save.png
ShiyongOllydbgConglingkaishiCracking/img/saved.png
ShiyongOllydbgConglingkaishiCracking/img/settings-s.png
ShiyongOllydbgConglingkaishiCracking/img/settings.png
ShiyongOllydbgConglingkaishiCracking/img/star.png
ShiyongOllydbgConglingkaishiCracking/js/__init__.py
ShiyongOllydbgConglingkaishiCracking/js/epub.js
ShiyongOllydbgConglingkaishiCracking/js/epub.min.js
ShiyongOllydbgConglingkaishiCracking/js/epub.min.map
ShiyongOllydbgConglingkaishiCracking/js/hooks.min.js
ShiyongOllydbgConglingkaishiCracking/js/hooks.min.map
ShiyongOllydbgConglingkaishiCracking/js/reader.js
ShiyongOllydbgConglingkaishiCracking/js/reader.js.map
shiyong_ollydbg_conglingkaishi_cracking-2024.3.2.0.dist-info/METADATA
shiyong_ollydbg_conglingkaishi_cracking-2024.3.2.0.dist-info/WHEEL
shiyong_ollydbg_conglingkaishi_cracking-2024.3.2.0.dist-info/entry_points.txt
shiyong_ollydbg_conglingkaishi_cracking-2024.3.2.0.dist-info/top_level.txt
shiyong_ollydbg_conglingkaishi_cracking-2024.3.2.0.dist-info/RECORD
